Metadata-Version: 1.1
Name: json-extensions
Version: 0.2.1.9.g9d1a9cb
Summary: Implements sereval JSON specs, like JSON Schema.
Home-page: https://github.com/johnnoone/json-extensions
Author: Xavier Barbosa
Author-email: clint.northwood@gmail.com
License: BSD
Keywords: setup
Platform: UNKNOWN
Classifier: Development Status :: 4 - Beta
Classifier: Environment :: Console
Classifier: Environment :: OpenStack
Classifier: Intended Audience :: Developers
Classifier: Intended Audience :: Information Technology
Classifier: License :: OSI Approved :: Apache Software License
Classifier: Operating System :: OS Independent
Classifier: Programming Language :: Python
